<annotation verified="yes">
	<folder>images</folder>
	<filename>waves-017534.jpg</filename>
	<path>/home/baptiste/Documents/waves_dataset/images/waves-017534.jpg</path>
	<source>
		<database>Unknown</database>
	</source>
	<size>
		<width>480</width>
		<height>320</height>
		<depth>3</depth>
	</size>
	<segmented>0</segmented>
	<object>
		<name>wave</name>
		<pose>Unspecified</pose>
		<truncated>0</truncated>
		<difficult>0</difficult>
		<bndbox>
			<xmin>14</xmin>
			<ymin>206</ymin>
			<xmax>145</xmax>
			<ymax>263</ymax>
		</bndbox>
	</object>
	<object>
		<name>wave</name>
		<pose>Unspecified</pose>
		<truncated>0</truncated>
		<difficult>0</difficult>
		<bndbox>
			<xmin>253</xmin>
			<ymin>145</ymin>
			<xmax>392</xmax>
			<ymax>189</ymax>
		</bndbox>
	</object>
	<object>
		<name>wave</name>
		<pose>Unspecified</pose>
		<truncated>0</truncated>
		<difficult>0</difficult>
		<bndbox>
			<xmin>13</xmin>
			<ymin>122</ymin>
			<xmax>165</xmax>
			<ymax>173</ymax>
		</bndbox>
	</object>
</annotation>
